backports/__init__.py
backports/zoneinfo/_tzpath.py
backports/zoneinfo/py.typed
backports/zoneinfo/_czoneinfo.cpython-36m-i386-linux-gnu.so
backports/zoneinfo/__init__.pyi
backports/zoneinfo/__init__.py
backports/zoneinfo/_common.py
backports/zoneinfo/_version.py
backports/zoneinfo/_zoneinfo.py
backports.zoneinfo-0.2.0.dist-info/RECORD
backports.zoneinfo-0.2.0.dist-info/WHEEL
backports.zoneinfo-0.2.0.dist-info/top_level.txt
backports.zoneinfo-0.2.0.dist-info/LICENSE_APACHE
backports.zoneinfo-0.2.0.dist-info/METADATA
backports.zoneinfo-0.2.0.dist-info/LICENSE
