Metadata-Version: 2.1
Name: backports.zoneinfo
Version: 0.2.0
Summary: Backport of the standard library zoneinfo module
Home-page: https://github.com/pganssle/zoneinfo
Author: Python Software Foundation
Author-email: datetime-sig@python.org
License: Apache-2.0
Project-URL: Source, https://github.com/pganssle/zoneinfo
Project-URL: Documentation, https://zoneinfo.readthedocs.io/en/latest/
Project-URL: Bug Reports, https://github.com/pganssle/zoneinfo/issues
Platform: UNKNOWN
Classifier: Development Status :: 4 - Beta
Classifier: Intended Audience :: Developers
Classifier: License :: OSI Approved :: Apache Software License
Classifier: Programming Language :: Python :: 3
Classifier: Programming Language :: Python :: 3 :: Only
Classifier: Programming Language :: Python :: 3.6
Classifier: Programming Language :: Python :: 3.7
Classifier: Programming Language :: Python :: 3.8
Requires-Python: >=3.6
Provides-Extra: tzdata
